README.txt
setup.py
Usurper.egg-info/PKG-INFO
Usurper.egg-info/SOURCES.txt
Usurper.egg-info/dependency_links.txt
Usurper.egg-info/requires.txt
Usurper.egg-info/top_level.txt
bin/usrpr
usurper/__init__.py
usurper/pos.py
usurper/soegaard.py
usurper/textrank.py
usurper/data/ar-padt.map
usurper/data/bg-btb.map
usurper/data/ca-cat3lb.map
usurper/data/cs-pdt.map
usurper/data/da-ddt.map
usurper/data/de-negra.map
usurper/data/de-tiger.map
usurper/data/el-gdt.map
usurper/data/en-brown.map
usurper/data/en-ptb.map
usurper/data/en-tweet.map
usurper/data/es-cast3lb.map
usurper/data/eu-eus3lb.map
usurper/data/fi-tdt.map
usurper/data/fr-paris.map
usurper/data/hu-szeged.map
usurper/data/it-isst.map
usurper/data/iw-mila.map
usurper/data/ja-kyoto.map
usurper/data/ja-verbmobil.map
usurper/data/ko-sejong.map
usurper/data/nl-alpino.map
usurper/data/pl-ipipan.map
usurper/data/pt-bosque.map
usurper/data/ru-rnc.map
usurper/data/sl-sdt.map
usurper/data/sv-talbanken.map
usurper/data/tu-metusbanci.map
usurper/data/zh-ctb6.map
usurper/data/zh-sinica.map
usurper/utils/__init__.py
usurper/utils/conll.py
usurper/utils/tsv.py