Metadata-Version: 1.1
Name: Usurper
Version: 0.9.0
Summary: An unsupervised dependency parser.
Home-page: http://pypi.python.org/pypi/Usurper/
Author: Thomas Proisl
Author-email: thopro@posteo.de
License: GNU General Public License v3 or later (GPLv3+)
Platform: UNKNOWN
Classifier: Development Status :: 5 - Production/Stable
Classifier: Environment :: Console
Classifier: License :: OSI Approved :: GNU General Public License v3 or later (GPLv3+)
Classifier: Operating System :: OS Independent
Classifier: Programming Language :: Python :: 2
Classifier: Programming Language :: Python :: 3
Classifier: Topic :: Scientific/Engineering :: Artificial Intelligence
Classifier: Topic :: Text Processing :: Linguistic
